{"chunk_definitions":[{"row":15,"row_count":1,"visible":true,"expansion_state":0,"options":{"engine":"r","label":"librarysetting","echo":false,"warning":false,"message":false},"document_id":"467227F3","chunk_id":"cf19wqpj8ozgx","chunk_label":"librarysetting"},{"row":41,"row_count":1,"visible":true,"expansion_state":0,"options":{"engine":"r","label":"themesetting","echo":false,"warning":false,"message":false},"document_id":"467227F3","chunk_id":"c5wdfcaz2l77q","chunk_label":"themesetting"},{"row":64,"row_count":1,"visible":true,"expansion_state":0,"options":{"engine":"r","label":"bbgenprofile2021","echo":false,"message":false,"warning":false},"document_id":"467227F3","chunk_id":"cf28f0uvhnf4c","chunk_label":"bbgenprofile2021"},{"row":83,"row_count":1,"visible":true,"expansion_state":0,"options":{"engine":"r","label":"bbgenprofile2022","echo":false,"message":false,"warning":false},"document_id":"467227F3","chunk_id":"cz3d0vzl9ehhf","chunk_label":"bbgenprofile2022"},{"row":101,"row_count":1,"visible":true,"expansion_state":0,"options":{"engine":"r","label":"plot_bbminegtnetgen2021","echo":false,"warning":false,"message":false},"document_id":"467227F3","chunk_id":"c4jms3a0n6nvd","chunk_label":"plot_bbminegtnetgen2021"},{"row":118,"row_count":1,"visible":true,"expansion_state":0,"options":{"engine":"r","label":"plot_bbminegtnetgen2022","echo":false,"warning":false,"message":false},"document_id":"467227F3","chunk_id":"c30hu9av6olub","chunk_label":"plot_bbminegtnetgen2022"},{"row":136,"row_count":1,"visible":true,"expansion_state":0,"options":{"engine":"r","label":"plot_bbmaxegtnetgen2021","echo":false,"warning":false,"message":false},"document_id":"467227F3","chunk_id":"cozuf28hvk4ly","chunk_label":"plot_bbmaxegtnetgen2021"},{"row":154,"row_count":1,"visible":true,"expansion_state":0,"options":{"engine":"r","label":"plot_bbmaxegtnetgen2022","echo":false,"warning":false,"message":false},"document_id":"467227F3","chunk_id":"c8v1hlmwjggdl","chunk_label":"plot_bbmaxegtnetgen2022"}],"doc_write_time":1689819351}